setup.py
maticv/LICENSE.txt
maticv/README.md
maticv/__init__.py
maticv/cv2.pyd
maticv/cv2.so
maticv/driver.py
maticv/maticv_client.zip
maticv/pattern.py
maticv.egg-info/PKG-INFO
maticv.egg-info/SOURCES.txt
maticv.egg-info/dependency_links.txt
maticv.egg-info/not-zip-safe
maticv.egg-info/requires.txt
maticv.egg-info/top_level.txt
maticv/build/ime_apk/MaticvKeyBoard.apk
maticv/build/platform-tools/AdbWinApi.dll
maticv/build/platform-tools/AdbWinUsbApi.dll
maticv/build/platform-tools/aapt
maticv/build/platform-tools/aapt.exe
maticv/build/platform-tools/adb
maticv/build/platform-tools/adb.exe
maticv/build/unlock_apk/unlock.apk
maticv/common/__init__.py
maticv/common/action.py
maticv/common/adb.py
maticv/common/app.py
maticv/common/gl.py
maticv/common/keys.py
maticv/common/match.py
maticv/common/pattern.py
maticv/common/region.py
maticv/common/screencap.py
maticv/common/utils.py
maticv/common/opencv/__init__.py
maticv/common/opencv/linux/__init__.py
maticv/common/opencv/linux/cv2.so
maticv/common/opencv/x64/__init__.py
maticv/common/opencv/x64/cv2.pyd
maticv/common/opencv/x86/__init__.py
maticv/common/opencv/x86/cv2.pyd